tests/__init__.py
tests/test_load_generator.py
tests/test_management_test.py
tests/test_monitoring_analysis.py
tests/test_performance_metrics.py
tests/test_request_customization.py
tests/test_scenario_definition.py
tstresser/__init__.py
tstresser/cli.py
tstresser/error_handling.py
tstresser/integration_automation.py
tstresser/load_generator.py
tstresser/management_test.py
tstresser/monitoring_analysis.py
tstresser/performance_metrics.py
tstresser/request_customization.py
tstresser/scenario_definition.py
tstresser/security_testing.py
tstresser/utils.py
tstresser-0.1.3.dist-info/LICENSE
tstresser-0.1.3.dist-info/METADATA
tstresser-0.1.3.dist-info/WHEEL
tstresser-0.1.3.dist-info/entry_points.txt
tstresser-0.1.3.dist-info/top_level.txt
tstresser-0.1.3.dist-info/RECORD
