Metadata-Version: 2.1
Name: tstresser
Version: 0.1.3
Summary: A CLI-based stress tester for web applications and APIs
Home-page: https://github.com/deestarks/t-stresser
Author: Daniel Onoja
Author-email: danielonoja246@gmail.com
Classifier: Programming Language :: Python :: 3
Classifier: License :: OSI Approved :: MIT License
Classifier: Operating System :: OS Independent
Requires-Python: >=3.6
License-File: LICENSE
Requires-Dist: matplotlib ==3.9.0
Requires-Dist: pytest ==8.2.2
Requires-Dist: requests ==2.32.3
Requires-Dist: requests-oauthlib ==2.0.0
Requires-Dist: tqdm ==4.66.4
